<?xml version="1.0" encoding="utf-8" ?><dwsync><file name="BaseCommand.php" server="192.168.1.118//reportcards/" local="3808543778" remote="3816177360" Dst="-1" /><file name="InputOutput.php" server="192.168.1.118//reportcards/" local="3808543778" remote="3816177360" Dst="-1" /><file name="CLI.php" server="192.168.1.118//reportcards/" local="3808543778" remote="3816177360" Dst="-1" /><file name="Commands.php" server="192.168.1.118//reportcards/" local="3808543778" remote="3816177360" Dst="-1" /><file name="Console.php" server="192.168.1.118//reportcards/" local="3808543778" remote="3816177360" Dst="-1" /><file name="GeneratorTrait.php" server="192.168.1.118//reportcards/" local="3808543778" remote="3816177360" Dst="-1" /><file name="BaseCommand.php" server="192.168.1.118//Codeigniter/" local="3808543778" remote="3816177540" Dst="-1" /><file name="InputOutput.php" server="192.168.1.118//Codeigniter/" local="3808543778" remote="3816177540" Dst="-1" /><file name="CLI.php" server="192.168.1.118//Codeigniter/" local="3808543778" remote="3816177540" Dst="-1" /><file name="Commands.php" server="192.168.1.118//Codeigniter/" local="3808543778" remote="3816177540" Dst="-1" /><file name="Console.php" server="192.168.1.118//Codeigniter/" local="3808543778" remote="3816177540" Dst="-1" /><file name="GeneratorTrait.php" server="192.168.1.118//Codeigniter/" local="3808543778" remote="3816177540" Dst="-1" /></dwsync>